LICENSE
MANIFEST.in
README.rst
runtests.py
setup.py
django_handlebars/__init__.py
django_handlebars/__init__.pyc
django_handlebars/appsettings.py
django_handlebars/appsettings.pyc
django_handlebars/models.py
django_handlebars/models.pyc
django_handlebars/tests.py
django_handlebars/tests.pyc
django_handlebars/utils.py
django_handlebars/utils.pyc
django_handlebars.egg-info/PKG-INFO
django_handlebars.egg-info/SOURCES.txt
django_handlebars.egg-info/dependency_links.txt
django_handlebars.egg-info/not-zip-safe
django_handlebars.egg-info/requires.txt
django_handlebars.egg-info/top_level.txt
django_handlebars/management/__init__.py
django_handlebars/management/__init__.pyc
django_handlebars/management/compiler.py
django_handlebars/management/compiler.pyc
django_handlebars/management/commands/__init__.py
django_handlebars/management/commands/__init__.pyc
django_handlebars/management/commands/compilehandlebars.py
django_handlebars/management/commands/compilehandlebars.pyc
django_handlebars/management/observer/__init__.py
django_handlebars/management/observer/__init__.pyc
django_handlebars/management/observer/base.py
django_handlebars/management/observer/base.pyc
django_handlebars/management/observer/inotify.py
django_handlebars/management/observer/inotify.pyc
django_handlebars/static/js/handlebars/handlebars.django.js
django_handlebars/static/js/handlebars/handlebars.js
django_handlebars/static/js/handlebars/handlebars.runtime.js
django_handlebars/templatetags/__init__.py
django_handlebars/templatetags/__init__.pyc
django_handlebars/templatetags/handlebars_tags.py
django_handlebars/templatetags/handlebars_tags.pyc