Metadata-Version: 1.0
Name: django-handlebars
Version: 0.1
Summary: Handlebars for Django
Home-page: https://github.com/yavorskiy/django-handlebars
Author: Sergii Iavorskyi
Author-email: yavorskiy.s@gmail.com
License: BSD
Download-URL: https://github.com/yavorskiy/django-handlebars/downloads
Keywords: django handlebars
Platform: UNKNOWN
Classifier: Development Status :: 4 - Beta
Classifier: Environment :: Web Environment
Classifier: Framework :: Django
Classifier: Intended Audience :: Developers
Classifier: Operating System :: OS Independent
Classifier: Programming Language :: Python
Classifier: Programming Language :: JavaScript
